Metadata-Version: 2.1
Name: cycuCourse
Version: 1.0.3
Summary: A Auxiliary package for CYCU course selection system.
Home-page: https://github.com/y252328/CYCU-Course-Selection-Helper
Author: y252328
Author-email: y252328@gmail.com
License: MIT
Project-URL: Bug Reports, https://github.com/y252328/CYCU-Course-Selection-Helper/issues
Project-URL: Source, https://github.com/y252328/CYCU-Course-Selection-Helper
Keywords: CYCU Course Selection 中原 選課
Platform: UNKNOWN
Classifier: License :: OSI Approved :: MIT License
Classifier: Natural Language :: Chinese (Traditional)
Classifier: Programming Language :: Python
Classifier: Programming Language :: Python :: 3.5
Classifier: Programming Language :: Python :: 3.6
